odoo/addons/account_invoice_section_sale_order/README.rst
odoo/addons/account_invoice_section_sale_order/__init__.py
odoo/addons/account_invoice_section_sale_order/__manifest__.py
odoo/addons/account_invoice_section_sale_order/i18n/account_invoice_section_sale_order.pot
odoo/addons/account_invoice_section_sale_order/i18n/ca.po
odoo/addons/account_invoice_section_sale_order/i18n/es.po
odoo/addons/account_invoice_section_sale_order/models/__init__.py
odoo/addons/account_invoice_section_sale_order/models/account_move.py
odoo/addons/account_invoice_section_sale_order/models/res_company.py
odoo/addons/account_invoice_section_sale_order/models/res_config_settings.py
odoo/addons/account_invoice_section_sale_order/models/res_partner.py
odoo/addons/account_invoice_section_sale_order/models/sale_order.py
odoo/addons/account_invoice_section_sale_order/readme/CONFIGURATION.rst
odoo/addons/account_invoice_section_sale_order/readme/CONTRIBUTORS.rst
odoo/addons/account_invoice_section_sale_order/readme/CREDITS.rst
odoo/addons/account_invoice_section_sale_order/readme/DESCRIPTION.rst
odoo/addons/account_invoice_section_sale_order/security/res_groups.xml
odoo/addons/account_invoice_section_sale_order/static/description/icon.png
odoo/addons/account_invoice_section_sale_order/static/description/index.html
odoo/addons/account_invoice_section_sale_order/tests/__init__.py
odoo/addons/account_invoice_section_sale_order/tests/common.py
odoo/addons/account_invoice_section_sale_order/tests/test_access_rights.py
odoo/addons/account_invoice_section_sale_order/tests/test_invoice_group_by_sale_order.py
odoo/addons/account_invoice_section_sale_order/views/res_config_settings.xml
odoo/addons/account_invoice_section_sale_order/views/res_partner.xml
odoo14_addon_account_invoice_section_sale_order-14.0.1.3.2.dist-info/METADATA
odoo14_addon_account_invoice_section_sale_order-14.0.1.3.2.dist-info/WHEEL
odoo14_addon_account_invoice_section_sale_order-14.0.1.3.2.dist-info/top_level.txt
odoo14_addon_account_invoice_section_sale_order-14.0.1.3.2.dist-info/RECORD
